tech_shrimp_diet_helper/__init__.py
tech_shrimp_diet_helper-0.1.1.dist-info/WHEEL
tech_shrimp_diet_helper-0.1.1.dist-info/entry_points.txt
tech_shrimp_diet_helper-0.1.1.dist-info/METADATA
tech_shrimp_diet_helper-0.1.1.dist-info/RECORD
