Metadata-Version: 2.3
Name: tech-shrimp-diet-helper
Version: 0.1.1
Summary: Add your description here
Requires-Dist: mcp[cli]>=1.14.0
Requires-Python: >=3.13
